MANIFEST.in
setup.cfg
setup.py
yadtreceiver/__init__.py
yadtreceiver/configuration.py
yadtreceiver/events.py
yadtreceiver/graphite.py
yadtreceiver/protocols.py
yadtreceiver/yadtreceiver
yadtreceiver/yadtreceiver.tac
yadtreceiver.egg-info/PKG-INFO
yadtreceiver.egg-info/SOURCES.txt
yadtreceiver.egg-info/dependency_links.txt
yadtreceiver.egg-info/requires.txt
yadtreceiver.egg-info/top_level.txt
yadtreceiver.egg-info/zip-safe