Metadata-Version: 1.1
Name: yadtreceiver
Version: 0.1.10
Summary: Executes yadtshell commands triggered by a yadtbroadcaster.
Home-page: https://github.com/yadt/yadtreceiver
Author: Arne Hilmann, Maximilien Riehl, Michael Gruber
Author-email: arne.hilmann@gmail.com, maximilien.riehl@gmail.com, aelgru@gmail.com
License: GNU GPL v3
Platform: UNKNOWN
Classifier: Development Status :: 3 - Alpha
Classifier: Programming Language :: Python
